gci/__init__.py
gci/componentmodel.py
gci/oci.py
ocm/VERSION
ocm/__init__.py
ocm_lib-0.0.1.dev0.dist-info/LICENSE
ocm_lib-0.0.1.dev0.dist-info/METADATA
ocm_lib-0.0.1.dev0.dist-info/WHEEL
ocm_lib-0.0.1.dev0.dist-info/top_level.txt
ocm_lib-0.0.1.dev0.dist-info/RECORD
