Metadata-Version: 2.1
Name: ocm-lib
Version: 0.0.1.dev0
Summary: Open-Component-Model (OCM) language bindings
Requires-Python: >=3.11
License-File: LICENSE
Requires-Dist: dacite
Requires-Dist: jsonschema
Requires-Dist: python-dateutil
Requires-Dist: PyYaml
